patata/__init__.py
patata/client.py
patata/exceptions.py
patata/models.py
patata-3.6.0.dist-info/METADATA
patata-3.6.0.dist-info/WHEEL
patata-3.6.0.dist-info/licenses/LICENSE
patata-3.6.0.dist-info/RECORD
