Metadata-Version: 2.1
Name: patata
Version: 3.6.0
Summary: Simple lightweight HTTP client to perform GET or POST requests in parallel with multiprocessing and in each process use aiohttp to do them concurrently and maximize the throughtput.
Project-URL: repository, https://github.com/oalfonso-o/patata
Project-URL: documentation, https://github.com/oalfonso-o/patata/blob/main/README.md
Author-email: Oriol Alfonso <oriol@oalfonso.com>
License: MIT License
License-File: LICENSE
Classifier: Development Status :: 4 - Beta
Classifier: Framework :: AsyncIO
Classifier: Framework :: aiohttp
Classifier: Intended Audience :: Developers
Classifier: Programming Language :: Python :: 3 :: Only
Classifier: Programming Language :: Python :: 3.8
Classifier: Programming Language :: Python :: 3.9
Classifier: Programming Language :: Python :: 3.10
Classifier: Programming Language :: Python :: 3.11
Requires-Python: >=3.8
Requires-Dist: aiohttp-retry<3,>=2.8.3
Requires-Dist: aiohttp<4,>=3.8.4
Requires-Dist: importlib-metadata; python_version < '3.9'
Requires-Dist: pydantic<2,>=1.9
